xid/__init__.py
xid/xid.py
py_xid-1.0.0.dist-info/LICENSE
py_xid-1.0.0.dist-info/METADATA
py_xid-1.0.0.dist-info/WHEEL
py_xid-1.0.0.dist-info/top_level.txt
py_xid-1.0.0.dist-info/RECORD
