Metadata-Version: 2.1
Name: py-xid
Version: 1.0.0
Summary: Globally unique identifier generator library
Home-page: https://github.com/alexferl/xid
Author: Alexandre Ferland
Author-email: me@alexferl.com
License: MIT
Classifier: Intended Audience :: Developers
Classifier: License :: OSI Approved :: MIT License
Classifier: Operating System :: OS Independent
Classifier: Programming Language :: Python :: 3.8
Classifier: Programming Language :: Python :: 3.9
Classifier: Programming Language :: Python :: 3.10
Classifier: Programming Language :: Python :: 3.11
Classifier: Topic :: Software Development :: Libraries :: Python Modules
Requires-Python: >=3.8
License-File: LICENSE
